setup.py
ckanext/__init__.py
ckanext/themeUrbanOpus/__init__.py
ckanext/themeUrbanOpus/plugin.py
ckanext_themeUrbanOpus.egg-info/PKG-INFO
ckanext_themeUrbanOpus.egg-info/SOURCES.txt
ckanext_themeUrbanOpus.egg-info/dependency_links.txt
ckanext_themeUrbanOpus.egg-info/entry_points.txt
ckanext_themeUrbanOpus.egg-info/namespace_packages.txt
ckanext_themeUrbanOpus.egg-info/not-zip-safe
ckanext_themeUrbanOpus.egg-info/top_level.txt