Metadata-Version: 1.0
Name: ckanext-themeUrbanOpus
Version: 0.1
Summary: This serves to override default ckan front-end components with Urban Opus theme.
Home-page: UNKNOWN
Author: UNKNOWN
Author-email: UNKNOWN
License: UNKNOWN
Platform: UNKNOWN
